{
  "$schema": "https://schema.management.azure.com/schemas/2019-04-01/deploymentParameters.json#",
  "contentVersion": "1.0.0.0",
  "parameters": {
    "location": {
      "value": "eastus"
    },
    "environment": {
      "value": "dev"
    },
    "appName": {
      "value": "quote"
    },
    "uniqueSuffix": {
      "value": "abc123"
    },
    "storageAccountSku": {
      "value": "Standard_LRS"
    },
    "functionAppRuntime": {
      "value": "node"
    },
    "functionAppRuntimeVersion": {
      "value": "20"
    },
    "functionAppPlanSku": {
      "value": "Y1"
    },
    "enableApplicationInsights": {
      "value": true
    },
    "sampleQuotes": {
      "value": [
        {
          "partitionKey": "inspiration",
          "rowKey": "001",
          "quote": "The only way to do great work is to love what you do.",
          "author": "Steve Jobs",
          "category": "motivation"
        },
        {
          "partitionKey": "inspiration",
          "rowKey": "002",
          "quote": "Innovation distinguishes between a leader and a follower.",
          "author": "Steve Jobs",
          "category": "innovation"
        },
        {
          "partitionKey": "inspiration",
          "rowKey": "003",
          "quote": "Success is not final, failure is not fatal.",
          "author": "Winston Churchill",
          "category": "perseverance"
        },
        {
          "partitionKey": "inspiration",
          "rowKey": "004",
          "quote": "The future belongs to those who believe in the beauty of their dreams.",
          "author": "Eleanor Roosevelt",
          "category": "dreams"
        },
        {
          "partitionKey": "inspiration",
          "rowKey": "005",
          "quote": "It is during our darkest moments that we must focus to see the light.",
          "author": "Aristotle",
          "category": "hope"
        },
        {
          "partitionKey": "inspiration",
          "rowKey": "006",
          "quote": "Be yourself; everyone else is already taken.",
          "author": "Oscar Wilde",
          "category": "authenticity"
        },
        {
          "partitionKey": "inspiration",
          "rowKey": "007",
          "quote": "Two things are infinite: the universe and human stupidity; and I'm not sure about the universe.",
          "author": "Albert Einstein",
          "category": "wisdom"
        },
        {
          "partitionKey": "inspiration",
          "rowKey": "008",
          "quote": "So many books, so little time.",
          "author": "Frank Zappa",
          "category": "learning"
        },
        {
          "partitionKey": "inspiration",
          "rowKey": "009",
          "quote": "A room without books is like a body without a soul.",
          "author": "Marcus Tullius Cicero",
          "category": "knowledge"
        },
        {
          "partitionKey": "inspiration",
          "rowKey": "010",
          "quote": "You only live once, but if you do it right, once is enough.",
          "author": "Mae West",
          "category": "life"
        }
      ]
    }
  }
}