{
  "$schema": "https://schema.management.azure.com/schemas/2019-04-01/deploymentParameters.json#",
  "contentVersion": "1.0.0.0",
  "parameters": {
    "location": {
      "value": "eastus"
    },
    "environment": {
      "value": "dev"
    },
    "namePrefix": {
      "value": "gov"
    },
    "nameSuffix": {
      "value": "demo01"
    },
    "logAnalyticsSkuName": {
      "value": "PerGB2018"
    },
    "logAnalyticsRetentionDays": {
      "value": 30
    },
    "enableAlerts": {
      "value": true
    },
    "alertEvaluationFrequency": {
      "value": 15
    },
    "alertSeverity": {
      "value": 2
    },
    "notificationEmail": {
      "value": "governance-team@yourcompany.com"
    },
    "slackWebhookUrl": {
      "value": ""
    },
    "resourceTags": {
      "value": {
        "Purpose": "Governance Dashboard",
        "Environment": "dev",
        "ManagedBy": "Bicep",
        "Project": "Azure Governance",
        "Owner": "IT Operations",
        "CostCenter": "IT-OPS-001",
        "CreatedDate": "2025-01-23",
        "Review": "Quarterly"
      }
    }
  }
}